setup.py
dsnd_probability_ivllt/Binomialdistribution.py
dsnd_probability_ivllt/Gaussiandistribution.py
dsnd_probability_ivllt/Generaldistribution.py
dsnd_probability_ivllt/__init__.py
dsnd_probability_ivllt.egg-info/PKG-INFO
dsnd_probability_ivllt.egg-info/SOURCES.txt
dsnd_probability_ivllt.egg-info/dependency_links.txt
dsnd_probability_ivllt.egg-info/not-zip-safe
dsnd_probability_ivllt.egg-info/top_level.txt