Metadata-Version: 1.0
Name: dsnd-probability-ivllt
Version: 1.1
Summary: Gaussian and Binomial distributions
Home-page: UNKNOWN
Author: Ivan Lau
Author-email: testing@hotmail.com
License: UNKNOWN
Platform: UNKNOWN
